{
    "version": "https://jsonfeed.org/version/1",
    "title": "白楠",
    "description": "",
    "home_page_url": "https://bainano.github.io/bainano.github.io",
    "feed_url": "https://bainano.github.io/bainano.github.io/feed.json",
    "user_comment": "",
    "author": {
        "name": "白楠"
    },
    "items": [
        {
            "id": "https://bainano.github.io/bainano.github.io/wen-xue.html",
            "url": "https://bainano.github.io/bainano.github.io/wen-xue.html",
            "title": "文章",
            "summary": "标题1 段落",
            "content_html": "\n    <h1 id=\"biao-ti-1\">\n      标题1\n    </h1>\n\n  <p>\n    \n  </p>\n\n    <h2 id=\"biao-ti-2\">\n      标题2\n    </h2>\n\n  <p>\n    \n  </p>\n\n    <h3 id=\"biao-ti-3\">\n      标题3\n    </h3>\n\n  <p>\n    \n  </p>\n\n    <h4 id=\"biao-ti-4\">\n      标题4\n    </h4>\n\n  <p>\n    \n  </p>\n\n    <h5 id=\"biao-ti-5\">\n      标题5\n    </h5>\n\n  <p>\n    \n  </p>\n\n    <h6 id=\"biao-ti-6\">\n      标题6\n    </h6>\n\n  <p>\n    \n  </p>\n\n  <p>\n    段落\n  </p>\n\n  <p>\n    \n  </p>\n\n    <figure class=\"blockquote\">\n      <blockquote>引用</blockquote>\n      <figcaption>引用作者</figcaption>\n    </figure>\n\n  <p>\n    \n  </p>",
            "author": {
                "name": "白楠"
            },
            "tags": [
                   "文学"
            ],
            "date_published": "2025-07-14T19:07:18+08:00",
            "date_modified": "2025-07-15T09:50:36+08:00"
        }
    ]
}
